argai/__init__.py
argai/base.py
argai/func.py
argai/storage.py
argai/utils.py
argai-0.0.5.dist-info/LICENSE
argai-0.0.5.dist-info/METADATA
argai-0.0.5.dist-info/WHEEL
argai-0.0.5.dist-info/top_level.txt
argai-0.0.5.dist-info/RECORD
