Metadata-Version: 2.1
Name: argai
Version: 0.0.5
Summary: Make any of your functions queryable with natural language.
Home-page: https://arg.ai/
Author: Jacky Koh
Author-email: jacky@arg.ai
License-File: LICENSE
Requires-Dist: openai
Requires-Dist: requests
Requires-Dist: pydantic
